sv/data_comparator.sv
module data_comparator(
    input logic clk,
    input logic rstn,
    input logic [9:0] inp1_i,
    input logic [9:0] inp2_i,
    input logic valid_i,
    output logic outp_o,
    output logic valid_o
);

    logic [5:0] res_internal;
    logic [5:0] valid_internal;

    always_ff @(posedge clk) begin
        if (!rstn) begin
            res_internal <= '0;
        end else begin
            if (valid_i) begin
                res_internal[0] <= (inp1_i == inp2_i);
            end
            res_internal[5:1] <= res_internal[4:0];
        end
    end

    always_ff @(posedge clk) begin
        if (!rstn) begin
            valid_internal <= '0;
        end else begin
            if (valid_i) begin
                valid_internal[0] <= '1;
            end
            valid_internal[5:1] <= valid_internal[4:0];
        end
    end

    assign outp_o = res_internal[5];
    assign valid_o = valid_internal[5];
endmodule

waveform.vcd
$version Generated by VerilatedVcd $end
$timescale 1ps $end
 $scope module TOP $end
  $var wire 1 " clk $end
  $var wire 1 # rstn $end
  $var wire 10 $ inp1_i [9:0] $end
  $var wire 10 % inp2_i [9:0] $end
  $var wire 1 & valid_i $end
  $var wire 1 ' outp_o $end
  $var wire 1 ( valid_o $end
  $scope module data_comparator $end
   $var wire 1 " clk $end
   $var wire 1 # rstn $end
   $var wire 10 $ inp1_i [9:0] $end
   $var wire 10 % inp2_i [9:0] $end
   $var wire 1 & valid_i $end
   $var wire 1 ' outp_o $end
   $var wire 1 ( valid_o $end
   $var wire 6 ) res_internal [5:0] $end
   $var wire 6 * valid_internal [5:0] $end
  $upscope $end
 $upscope $end
$enddefinitions $end


#0
1"
1#
b0101100111 $
b0101100111 %
1&
0'
0(
b000000 )
b000000 *
#1
0"
#2
1"
b1111000110 $
b1111000110 %
b000001 )
b000001 *
#3
0"
#4
1"
b0001101001 $
b0001101001 %
b000011 )
b000011 *
#5
0"
#6
1"
b0001110011 $
b0001110011 %
b000111 )
b000111 *
#7
0"
#8
1"
b0001010001 $
b0001010001 %
b001111 )
b001111 *
#9
0"
#10
1"
b0011111111 $
b0011111111 %
0&
b011111 )
b011111 *
#11
0"
#12
1"
0#
b0001001010 $
b0001001010 %
1&
1'
1(
b111111 )
b111111 *
#13
0"
#14
1"
1#
b0011101100 $
b0011101100 %
0'
0(
b000000 )
b000000 *
#15
0"
#16
1"
b000001 )
b000001 *
#17
0"
#18
1"
b000011 )
b000011 *
#19
0"
#20
1"
b000111 )
b000111 *
#21
0"
#22
1"
b001111 )
b001111 *
#23
0"
#24
1"
b011111 )
b011111 *
#25
0"
#26
1"
1'
1(
b111111 )
b111111 *
